datetime_tz/__init__.py
datetime_tz/detect_windows.py
datetime_tz/pytz_abbr.py
datetime_tz/update_win32tz_map.py
datetime_tz/win32tz_map.py
python_datetime_tz-0.5.4.dist-info/LICENSE
python_datetime_tz-0.5.4.dist-info/METADATA
python_datetime_tz-0.5.4.dist-info/WHEEL
python_datetime_tz-0.5.4.dist-info/top_level.txt
python_datetime_tz-0.5.4.dist-info/RECORD
