Metadata-Version: 2.1
Name: python-datetime-tz
Version: 0.5.4
Summary: A drop in replacement for Python's datetime module which cares deeply about timezones.
Requires-Dist: pytz (>=2011g)
Requires-Dist: python-dateutil (>=2.0)
